hanlp/__init__.py
hanlp/parsers.py
hanlp/utils.py
hanlp_wrapper-0.1.2.dist-info/DESCRIPTION.rst
hanlp_wrapper-0.1.2.dist-info/METADATA
hanlp_wrapper-0.1.2.dist-info/RECORD
hanlp_wrapper-0.1.2.dist-info/WHEEL
hanlp_wrapper-0.1.2.dist-info/metadata.json
hanlp_wrapper-0.1.2.dist-info/top_level.txt
