Metadata-Version: 2.0
Name: hanlp-wrapper
Version: 0.1.2
Summary: HanLP wrapper in python
Home-page: https://github.com/longquanj/HanLP-py.git
Author: Longquan JIANG
Author-email: longquan.jiang@outlook.com
License: Apache License 2.0
Keywords: hanlp python segment
Platform: Operating System :: MacOS :: MacOS X
Platform: Operating System :: Microsoft :: Windows :: Windows 7
Platform: Operating System :: Microsoft :: Windows :: Windows Vista
Platform: Operating System :: POSIX :: Linux
Classifier: Intended Audience :: Developers
Classifier: Programming Language :: Python
Classifier: Programming Language :: Python :: 2.6
Classifier: Programming Language :: Python :: 2.7
Classifier: Programming Language :: Python :: 3
Classifier: Programming Language :: Python :: 3.4
Classifier: Programming Language :: Python :: 3.5
Classifier: Programming Language :: Python :: 3.6
Classifier: Topic :: Utilities
Requires-Dist: JPype1
Requires-Dist: pyyaml
